{"cameraMode":{"drawMode":0,"name":"Shaded","section":"Shading Mode"},"sceneLighting":true,"audioPlay":false,"sceneViewState":{"showFog":true,"showMaterialUpdate":false,"showSkybox":true,"showFlares":true,"showImageEffects":true,"showParticleSystems":true},"in2DMode":false,"pivot":{"x":10.041404724121094,"y":18.812538146972658,"z":7.0255513191223148},"rotation":{"x":-0.01901407353579998,"y":0.9417431354522705,"z":-0.054030705243349078,"w":-0.33141982555389407},"size":4.989323139190674,"orthographic":false}